pycounts_ppp_his/__init__.py
pycounts_ppp_his/pycounts_ppp_his.py
pycounts_ppp_his-0.1.0.dist-info/LICENSE
pycounts_ppp_his-0.1.0.dist-info/METADATA
pycounts_ppp_his-0.1.0.dist-info/WHEEL
pycounts_ppp_his-0.1.0.dist-info/RECORD
